odoo9_addon_mrp_sale_info-9.0.1.0.0.99.dev17-py2.7-nspkg.pth
odoo9_addon_mrp_sale_info-9.0.1.0.0.99.dev17.dist-info/DESCRIPTION.rst
odoo9_addon_mrp_sale_info-9.0.1.0.0.99.dev17.dist-info/METADATA
odoo9_addon_mrp_sale_info-9.0.1.0.0.99.dev17.dist-info/RECORD
odoo9_addon_mrp_sale_info-9.0.1.0.0.99.dev17.dist-info/WHEEL
odoo9_addon_mrp_sale_info-9.0.1.0.0.99.dev17.dist-info/metadata.json
odoo9_addon_mrp_sale_info-9.0.1.0.0.99.dev17.dist-info/namespace_packages.txt
odoo9_addon_mrp_sale_info-9.0.1.0.0.99.dev17.dist-info/top_level.txt
odoo_addons/mrp_sale_info/README.rst
odoo_addons/mrp_sale_info/__init__.py
odoo_addons/mrp_sale_info/__openerp__.py
odoo_addons/mrp_sale_info/i18n/bg.po
odoo_addons/mrp_sale_info/i18n/ca.po
odoo_addons/mrp_sale_info/i18n/de.po
odoo_addons/mrp_sale_info/i18n/el_GR.po
odoo_addons/mrp_sale_info/i18n/es.po
odoo_addons/mrp_sale_info/i18n/es_MX.po
odoo_addons/mrp_sale_info/i18n/eu_ES.po
odoo_addons/mrp_sale_info/i18n/fi.po
odoo_addons/mrp_sale_info/i18n/fr.po
odoo_addons/mrp_sale_info/i18n/gl.po
odoo_addons/mrp_sale_info/i18n/hr.po
odoo_addons/mrp_sale_info/i18n/it.po
odoo_addons/mrp_sale_info/i18n/mrp_sale_info.pot
odoo_addons/mrp_sale_info/i18n/nl.po
odoo_addons/mrp_sale_info/i18n/nl_NL.po
odoo_addons/mrp_sale_info/i18n/pt_BR.po
odoo_addons/mrp_sale_info/i18n/pt_PT.po
odoo_addons/mrp_sale_info/i18n/sk.po
odoo_addons/mrp_sale_info/i18n/sl.po
odoo_addons/mrp_sale_info/i18n/tr.po
odoo_addons/mrp_sale_info/i18n/tr_TR.po
odoo_addons/mrp_sale_info/i18n/zh_CN.po
odoo_addons/mrp_sale_info/models/__init__.py
odoo_addons/mrp_sale_info/models/mrp_production.py
odoo_addons/mrp_sale_info/models/mrp_production_workcenter_line.py
odoo_addons/mrp_sale_info/static/description/icon.png
odoo_addons/mrp_sale_info/views/mrp_production.xml
odoo_addons/mrp_sale_info/views/mrp_production_workcenter_line.xml
